palom/.dev/mask-to-polygon.py
palom/.dev/test-difficult-cases.py
palom/__init__.py
palom/align.py
palom/align_multi_obj.py
palom/align_multi_res.py
palom/block_affine.py
palom/cli/__init__.py
palom/cli/align_he.py
palom/cli/compress_rgb_jpeg.py
palom/cli/doc/align_he.md
palom/cli/flow.py
palom/cli/helper.py
palom/cli/pyramid_tools.py
palom/cli/schema/__init__.py
palom/cli/schema/svs-config-example.yml
palom/cli/schema/svs-config-schema.yml
palom/cli/svs.py
palom/color.py
palom/extract.py
palom/img_util.py
palom/openslide_store.py
palom/pyramid.py
palom/reader.py
palom/register.py
palom/register_dev.py
palom/register_util.py
palom/slideio_store.py
palom-2025.7.1.dist-info/LICENSE
palom-2025.7.1.dist-info/METADATA
palom-2025.7.1.dist-info/WHEEL
palom-2025.7.1.dist-info/entry_points.txt
palom-2025.7.1.dist-info/RECORD
