Metadata-Version: 2.3
Name: palom
Version: 2025.7.1
Summary: Piecewise alignment for layers of mosaics
License: MIT
Keywords: microscopy,multiplex imaging,image registration,digital pathology,atlas
Author: Yu-An Chen
Author-email: atwood12@gmail.com
Requires-Python: >=3.10
Classifier: License :: OSI Approved :: MIT License
Classifier: Programming Language :: Python :: 3
Classifier: Programming Language :: Python :: 3.10
Classifier: Programming Language :: Python :: 3.11
Classifier: Programming Language :: Python :: 3.12
Classifier: Programming Language :: Python :: 3.13
Provides-Extra: all
Provides-Extra: openslide
Provides-Extra: vsi
Requires-Dist: dask (>=2021.10.0)
Requires-Dist: fire (>=0.6.0)
Requires-Dist: imagecodecs (>=2021.11.11)
Requires-Dist: loguru (>=0.5.3)
Requires-Dist: matplotlib (>=3.4.3)
Requires-Dist: numpy (<2)
Requires-Dist: ome-types (>=0.5)
Requires-Dist: opencv-python-headless (>=4.9)
Requires-Dist: openslide-bin (>=4.0.0.2) ; extra == "openslide"
Requires-Dist: openslide-python (>=1.3)
Requires-Dist: palom[openslide,vsi] ; extra == "all"
Requires-Dist: pint (>=0.21)
Requires-Dist: scikit-image (>=0.18,<0.20)
Requires-Dist: scikit-learn (>=0.24)
Requires-Dist: slideio (>=2.7.1) ; extra == "vsi"
Requires-Dist: tifffile (>=2021.10.12,<=2024.7.2)
Requires-Dist: tqdm (>=4.62.3)
Requires-Dist: yamale (>=4,<5)
Requires-Dist: zarr (>=2.17,<3)
Project-URL: Homepage, https://pypi.org/project/palom/
Project-URL: Repository, https://github.com/Yu-AnChen/palom
